nb_cpp.cpython-37m-x86_64-linux-gnu.so
nb_cpp-0.0.8.dist-info/WHEEL
nb_cpp-0.0.8.dist-info/top_level.txt
nb_cpp-0.0.8.dist-info/METADATA
nb_cpp-0.0.8.dist-info/RECORD
nb_cpp-0.0.8.data/data/requirements-dev.txt
