Metadata-Version: 2.1
Name: nb-cpp
Version: 0.0.8
Summary: Newton Basins implementation in C++ (pybind11)
Home-page: UNKNOWN
Author: gmagno
Author-email: goncalo.magno@gmail.com
License: UNKNOWN
Platform: UNKNOWN
Classifier: Development Status :: 3 - Alpha
Classifier: Intended Audience :: Developers
Classifier: License :: OSI Approved :: MIT License
Classifier: Topic :: Scientific/Engineering
Classifier: Programming Language :: Python :: 3
Provides-Extra: dev
